python_module/__init__.py
python_module/add.py
python_module/subtract.py
python_module/extras/__init__.py
python_module/extras/divide.py
python_module/extras/multiply.py
python_module-0.1.5.dist-info/METADATA
python_module-0.1.5.dist-info/WHEEL
python_module-0.1.5.dist-info/top_level.txt
python_module-0.1.5.dist-info/RECORD
