Metadata-Version: 2.1
Name: python-module
Version: 0.1.5
Summary: My first Python package
Home-page: UNKNOWN
Author: Jesse Stone
Author-email: jessecharles@gmail.com
License: UNKNOWN
Keywords: python,first package
Platform: UNKNOWN
Classifier: Development Status :: 3 - Alpha
Classifier: Intended Audience :: Education
Classifier: Programming Language :: Python :: 2
Classifier: Programming Language :: Python :: 3
Classifier: Operating System :: MacOS :: MacOS X
Classifier: Operating System :: Microsoft :: Windows
